dolphin/__init__.py
dolphin/__main__.py
dolphin/audio.py
dolphin/beam_search.py
dolphin/constants.py
dolphin/languages.py
dolphin/model.py
dolphin/scorefilter.py
dolphin/transcribe.py
dolphin/version.py
dolphin/assets/bpe.model
dolphin/assets/config.yaml
dolphin/assets/feats_stats.npz
dataoceanai_dolphin-20250716.dist-info/METADATA
dataoceanai_dolphin-20250716.dist-info/WHEEL
dataoceanai_dolphin-20250716.dist-info/entry_points.txt
dataoceanai_dolphin-20250716.dist-info/top_level.txt
dataoceanai_dolphin-20250716.dist-info/RECORD
