Metadata-Version: 2.1
Name: dataoceanai-dolphin
Version: 20250716
Summary: DataoceanAI Open-source Large Speech Model
Home-page: https://github.com/DataoceanAI/dolphin
Author: DataoceanAI
License: Apache-2.0
Requires-Python: >=3.7
Requires-Dist: espnet ==202402
Requires-Dist: modelscope
Requires-Dist: addict ==2.4.0
Requires-Dist: pydub
Requires-Dist: funasr
Provides-Extra: dev
Requires-Dist: pytest ; extra == 'dev'
Requires-Dist: flake8 ; extra == 'dev'
